skyrim/common.py
skyrim/forecast.py
skyrim/client/__init__.py
skyrim/core/__init__.py
skyrim/core/consts.py
skyrim/core/fetch.py
skyrim/core/skyrim.py
skyrim/core/utils.py
skyrim/core/models/__init__.py
skyrim/core/models/base.py
skyrim/core/models/dlwp.py
skyrim/core/models/ensemble.py
skyrim/core/models/fourcastnet.py
skyrim/core/models/fourcastnet_v2.py
skyrim/core/models/fuxi.py
skyrim/core/models/graphcast.py
skyrim/core/models/pangu.py
skyrim/core/models/utils.py
skyrim/libs/__init__.py
skyrim/libs/finetune/__init__.py
skyrim/libs/ic/__init__.py
skyrim/libs/ic/ifs.py
skyrim/libs/plotting/__init__.py
skyrim/libs/plotting/generate_rollout_gif.py
skyrim/libs/plotting/plot_wind_speed.py
skyrim/modal/forecast.py
Skyrim-0.0.2.dist-info/LICENSE
Skyrim-0.0.2.dist-info/METADATA
Skyrim-0.0.2.dist-info/WHEEL
Skyrim-0.0.2.dist-info/entry_points.txt
Skyrim-0.0.2.dist-info/top_level.txt
Skyrim-0.0.2.dist-info/RECORD
