Metadata-Version: 2.1
Name: Skyrim
Version: 0.0.2
Summary: AI weather models united.
Maintainer-email: SecondLaw Research <efe@2lw.ai>, SecondLaw Research <murat@2lw.ai>
License: Apache License
Project-URL: Homepage, https://github.com/secondlaw-ai/skyrim
Project-URL: Tracker, https://github.com/secondlaw-ai/skyrim/issues
Project-URL: Docs, https://github.com/secondlaw-ai/skyrim
Keywords: pytorch,weather,forecasting,ai,ml,xarray,dl
Classifier: License :: OSI Approved :: MIT License
Classifier: Programming Language :: Python
Classifier: Programming Language :: Python :: 3
Requires-Python: >=3.10
License-File: LICENSE
Requires-Dist: modal
Requires-Dist: loguru
Requires-Dist: xarray[zarr]
Requires-Dist: base58
Requires-Dist: botocore
Requires-Dist: aiobotocore
Requires-Dist: boto3
Requires-Dist: s3fs ==0.4.2
Requires-Dist: zarr
Requires-Dist: scipy
Requires-Dist: pandas
Requires-Dist: click
Provides-Extra: dev
Requires-Dist: black ; extra == 'dev'
Requires-Dist: ruff ; extra == 'dev'
Requires-Dist: pytest ; extra == 'dev'
Requires-Dist: tox ; extra == 'dev'
Requires-Dist: bumpver ; extra == 'dev'
Requires-Dist: coverage ; extra == 'dev'
Requires-Dist: twine ; extra == 'dev'
Requires-Dist: build ; extra == 'dev'
